ua_parser_builtins/__init__.py
ua_parser_builtins/py.typed
ua_parser_builtins/lazy.py
ua_parser_builtins/matchers.py
ua_parser_builtins/regexes.py
ua_parser_builtins-0.16.0.post1.dist-info/METADATA
ua_parser_builtins-0.16.0.post1.dist-info/WHEEL
ua_parser_builtins-0.16.0.post1.dist-info/RECORD
